Metadata-Version: 2.1
Name: splernfast
Version: 1.0.0
Summary: A Powerful package to perform different types of stable and unstable Sorting techniques on the list Data Structure.
Home-page: https://github.com/srimani-programmer/pysort
Author: Sri Manikanta Palakollu
Author-email: srimani.crypter@gmail.com
License: MIT
Classifier: License :: OSI Approved :: MIT License
Classifier: Programming Language :: Python :: 3
Classifier: Programming Language :: Python :: 3.7
Classifier: Programming Language :: Python :: 3.6
Classifier: Programming Language :: Python :: 3.5
Classifier: Programming Language :: Python :: 3.5
Classifier: Intended Audience :: Developers
Classifier: Operating System :: OS Independent
Classifier: Topic :: Software Development :: Libraries :: Python Modules
License-File: LICENSE
